{
  "bhozukwumchuma": {
    "1": "\u001d",
    "3": " ",
    "4": "!",
    "5": "\"",
    "6": "#",
    "7": "$",
    "8": "%",
    "9": "&",
    "10": "'",
    "11": "(",
    "12": ")",
    "13": "*",
    "14": "+",
    "15": ",",
    "16": "-",
    "17": ".",
    "18": "/",
    "19": "0",
    "20": "1",
    "21": "2",
    "22": "3",
    "23": "4",
    "24": "5",
    "25": "6",
    "26": "7",
    "27": "8",
    "28": "9",
    "29": ":",
    "30": ";",
    "31": "<",
    "32": "=",
    "33": ">",
    "34": "?",
    "35": "@",
    "36": "A",
    "37": "B",
    "38": "C",
    "39": "D",
    "40": "E",
    "41": "F",
    "42": "G",
    "43": "H",
    "44": "I",
    "45": "J",
    "46": "K",
    "47": "L",
    "48": "M",
    "49": "N",
    "50": "O",
    "51": "P",
    "52": "Q",
    "53": "R",
    "54": "S",
    "55": "T",
    "56": "U",
    "57": "V",
    "58": "W",
    "59": "X",
    "60": "Y",
    "61": "Z",
    "62": "[",
    "63": "\\",
    "64": "]",
    "65": "^",
    "66": "_",
    "67": "`",
    "68": "a",
    "69": "b",
    "70": "c",
    "71": "d",
    "72": "e",
    "73": "f",
    "74": "g",
    "75": "h",
    "76": "i",
    "77": "j",
    "78": "k",
    "79": "l",
    "80": "m",
    "81": "n",
    "82": "o",
    "83": "p",
    "84": "q",
    "85": "r",
    "86": "s",
    "87": "t",
    "88": "u",
    "89": "v",
    "90": "w",
    "91": "x",
    "92": "y",
    "93": "z",
    "94": "{",
    "95": "|",
    "96": "}",
    "97": "~",
    "98": "вҖҡ",
    "99": "Ж’",
    "100": "вҖһ",
    "101": "вҖҰ",
    "102": "вҖ ",
    "103": "вҖЎ",
    "104": "вҖ°",
    "105": "вҖ№",
    "106": "Е’",
    "107": "вҖҳ",
    "108": "вҖҷ",
    "109": "вҖң",
    "110": "вҖқ",
    "111": "вҖў",
    "112": "вҖ“",
    "113": "вҖ”",
    "114": "в„ў",
    "115": "вҖә",
    "116": "Е“",
    "117": "Её",
    "118": "В ",
    "119": "ВЎ",
    "120": "Вў",
    "121": "ВЈ",
    "122": "ВӨ",
    "123": "ВҘ",
    "124": "В§",
    "125": "ВЁ",
    "126": "ЛҶ",
    "127": "Лң",
    "128": "В©",
    "129": "ВӘ",
    "130": "В«",
    "131": "В¬",
    "132": "В®",
    "133": "ВҜ",
    "134": "В°",
    "135": "Вұ",
    "136": "Вҙ",
    "137": "Ој",
    "138": "В¶",
    "139": "вҲҷ",
    "140": "Вё",
    "141": "Вә",
    "142": "В»",
    "143": "Вҝ",
    "144": "ГҖ",
    "145": "ГҒ",
    "146": "ГӮ",
    "147": "Гғ",
    "148": "Г„",
    "149": "Г…",
    "150": "ГҶ",
    "151": "ГҮ",
    "152": "ГҲ",
    "153": "Гү",
    "154": "ГҠ",
    "155": "ГӢ",
    "156": "ГҢ",
    "157": "ГҚ",
    "158": "ГҺ",
    "159": "ГҸ",
    "160": "Г‘",
    "161": "Г’",
    "162": "Г“",
    "163": "Г”",
    "164": "Г•",
    "165": "Г–",
    "166": "Гҳ",
    "167": "Гҷ",
    "168": "Гҡ",
    "169": "Гӣ",
    "170": "Гң",
    "171": "Гҹ",
    "172": "Г ",
    "173": "ГЎ",
    "174": "Гў",
    "175": "ГЈ",
    "176": "ГӨ",
    "177": "ГҘ",
    "178": "ГҰ",
    "179": "Г§",
    "180": "ГЁ",
    "181": "Г©",
    "182": "ГӘ",
    "183": "Г«",
    "184": "Г¬",
    "185": "Гӯ",
    "186": "Г®",
    "187": "ГҜ",
    "188": "Гұ",
    "189": "ГІ",
    "190": "Гі",
    "191": "Гҙ",
    "192": "Гө",
    "193": "Г¶",
    "194": "Г·",
    "195": "Гё",
    "196": "Г№",
    "197": "Гә",
    "198": "Г»",
    "199": "Гј",
    "200": "Гҝ",
    "201": "вӮ¬",
    "202": "Е ",
    "203": "ЕҪ",
    "204": "ЕЎ",
    "205": "Еҫ",
    "206": "ВҰ",
    "207": "Вӯ",
    "208": "ВІ",
    "209": "Ві",
    "210": "В№",
    "211": "Вј",
    "212": "ВҪ",
    "213": "Вҫ",
    "214": "Гҗ",
    "215": "Г—",
    "216": "Гқ",
    "217": "Гһ",
    "218": "Г°",
    "219": "ГҪ",
    "220": "Гҫ",
    "221": "вҖҢ",
    "222": "вҖҚ",
    "223": "в—Ң",
    "224": "гҖҲ",
    "225": "гҖү",
    "226": "гҖҠ",
    "227": "гҖӢ",
    "228": "гҖҗ",
    "229": "гҖ‘",
    "230": "гҖ”",
    "231": "гҖ•",
    "232": "гҖң",
    "233": "гҖқ",
    "234": "гҖһ",
    "235": "гҖҹ",
    "236": "ајҖ",
    "237": "ај„",
    "238": "ај…",
    "239": "ајҲ",
    "240": "ајӢ",
    "241": "ајҢ",
    "242": "ајҚ",
    "243": "ајҺ",
    "244": "ај”",
    "245": "ајҡ",
    "246": "ајӣ",
    "247": "ајң",
    "248": "ајқ",
    "249": "ајһ",
    "250": "ајҹ",
    "251": "ај ",
    "252": "ајЎ",
    "253": "ајў",
    "254": "ајЈ",
    "255": "ајӨ",
    "256": "ајҘ",
    "257": "ајҰ",
    "258": "ај§",
    "259": "ајЁ",
    "260": "ај©",
    "261": "ајө",
    "262": "ај·",
    "263": "ајё",
    "264": "ај№",
    "265": "ајј",
    "266": "ајҪ",
    "267": "ајҫ",
    "268": "ајҝ",
    "269": "аҪҖ",
    "270": "аҪҒ",
    "271": "аҪӮ",
    "272": "аҪғ",
    "273": "аҪ„",
    "274": "аҪ…",
    "275": "аҪҶ",
    "276": "аҪҮ",
    "277": "аҪү",
    "278": "аҪҠ",
    "279": "аҪӢ",
    "280": "аҪҢ",
    "281": "аҪҚ",
    "282": "аҪҺ",
    "283": "аҪҸ",
    "284": "аҪҗ",
    "285": "аҪ‘",
    "286": "аҪ’",
    "287": "аҪ“",
    "288": "аҪ”",
    "289": "аҪ•",
    "290": "аҪ–",
    "291": "аҪ—",
    "292": "аҪҳ",
    "293": "аҪҷ",
    "294": "аҪҡ",
    "295": "аҪӣ",
    "296": "аҪң",
    "297": "аҪқ",
    "298": "аҪһ",
    "299": "аҪҹ",
    "300": "аҪ ",
    "301": "аҪЎ",
    "302": "аҪў",
    "303": "аҪЈ",
    "304": "аҪӨ",
    "305": "аҪҘ",
    "306": "аҪҰ",
    "307": "аҪ§",
    "308": "аҪЁ",
    "309": "аҪ©",
    "310": "аҪӘ",
    "311": "аҪұ",
    "312": "аҪІ",
    "313": "аҪі",
    "314": "аҪҙ",
    "315": "аҪө",
    "316": "аҪә",
    "317": "аҪ»",
    "318": "аҪј",
    "319": "аҪҫ",
    "320": "аҪҝ",
    "321": "аҫҖ",
    "322": "аҫҒ",
    "323": "аҫӮ",
    "324": "аҫғ",
    "325": "аҫ„",
    "326": "аҫҶ",
    "327": "аҫҮ",
    "328": "аҫҗ",
    "329": "аҫ‘",
    "330": "аҫ’",
    "331": "аҫ“",
    "332": "аҫ”",
    "333": "аҫ•",
    "334": "аҫ–",
    "335": "аҫ—",
    "336": "аҫҷ",
    "337": "аҫҡ",
    "338": "аҫӣ",
    "339": "аҫң",
    "340": "аҫқ",
    "341": "аҫһ",
    "342": "аҫҹ",
    "343": "аҫ ",
    "344": "аҫЎ",
    "345": "аҫў",
    "346": "аҫЈ",
    "347": "аҫӨ",
    "348": "аҫҘ",
    "349": "аҫҰ",
    "350": "аҫ§",
    "351": "аҫЁ",
    "352": "аҫ©",
    "353": "аҫӘ",
    "354": "аҫ«",
    "355": "аҫ¬",
    "356": "аҫӯ",
    "357": "аҫ®",
    "358": "аҫҜ",
    "359": "аҫ°",
    "360": "аҫұ",
    "361": "аҫІ",
    "362": "аҫі",
    "363": "аҫҙ",
    "364": "аҫө",
    "365": "аҫ¶",
    "366": "аҫ·",
    "367": "аҫё",
    "368": "аҫ№",
    "369": "аҫә",
    "370": "аҫ»",
    "371": "аҫј",
    "372": "аҪў",
    "373": "аҪІ",
    "374": "аҪәаҪҫ",
    "375": "аҪә",
    "376": "аҪ»",
    "377": "аҪјаҪҫ",
    "378": "аҪјаҫғ",
    "379": "аҪј",
    "380": "аҪјаҪҫ",
    "381": "аҪјаҫғ",
    "382": "аҫҖ",
    "383": "аҪҖаҪҙ",
    "384": "аҪҖаҫұ",
    "385": "аҪҖаҫұаҪҙ",
    "386": "аҪҖаҫІ",
    "387": "аҪҖаҫІаҪҙ",
    "388": "аҪҖаҫі",
    "389": "аҪҖаҫіаҪҙ",
    "390": "аҪўаҫҗ",
    "391": "аҪўаҫҗаҪҙ",
    "392": "аҪўаҫҗаҫұ",
    "393": "аҪўаҫҗаҫұаҪҙ",
    "394": "аҪЈаҫҗ",
    "395": "аҪЈаҫҗаҪҙ",
    "396": "аҪҰаҫҗ",
    "397": "аҪҰаҫҗаҪҙ",
    "398": "аҪҰаҫҗаҫұ",
    "399": "аҪҰаҫҗаҫұаҪҙ",
    "400": "аҪҰаҫҗаҫІ",
    "401": "аҪҰаҫҗаҫІаҪҙ",
    "402": "аҪҒаҪҙ",
    "403": "аҪҒаҫұ",
    "404": "аҪҒаҫұаҪҙ",
    "405": "аҪҒаҫІ",
    "406": "аҪҒаҫІаҪҙ",
    "407": "аҪӮаҪҙ",
    "408": "аҪӮаҫұ",
    "409": "аҪӮаҫұаҪҙ",
    "410": "аҪӮаҫІ",
    "411": "аҪӮаҫІаҪҙ",
    "412": "аҪӮаҫі",
    "413": "аҪӮаҫіаҪҙ",
    "414": "аҪўаҫ’",
    "415": "аҪўаҫ’аҪҙ",
    "416": "аҪўаҫ’аҫұ",
    "417": "аҪўаҫ’аҫұаҪҙ",
    "418": "аҪЈаҫ’",
    "419": "аҪЈаҫ’аҪҙ",
    "420": "аҪҰаҫ’",
    "421": "аҪҰаҫ’аҪҙ",
    "422": "аҪҰаҫ’аҫұ",
    "423": "аҪҰаҫ’аҫұаҪҙ",
    "424": "аҪҰаҫ’аҫІ",
    "425": "аҪҰаҫ’аҫІаҪҙ",
    "426": "аҪ„аҪҙ",
    "427": "аҪўаҫ”",
    "428": "аҪўаҫ”аҪҙ",
    "429": "аҪЈаҫ”",
    "430": "аҪЈаҫ”аҪҙ",
    "431": "аҪҰаҫ”",
    "432": "аҪҰаҫ”аҪҙ",
    "433": "аҪ…аҪҙ",
    "434": "аҪЈаҫ•",
    "435": "аҪЈаҫ•аҪҙ",
    "436": "аҪҶаҪҙ",
    "437": "аҪҮаҪҙ",
    "438": "аҪўаҫ—",
    "439": "аҪўаҫ—аҪҙ",
    "440": "аҪЈаҫ—",
    "441": "аҪЈаҫ—аҪҙ",
    "442": "аҪүаҪҙ",
    "443": "аҪўаҫҷ",
    "444": "аҪўаҫҷаҪҙ",
    "445": "аҪҰаҫҷ",
    "446": "аҪҰаҫҷаҪҙ",
    "447": "аҪҸаҪҙ",
    "448": "аҪҸаҫІ",
    "450": "аҪўаҫҹ",
    "451": "аҪўаҫҹаҪҙ",
    "452": "аҪЈаҫҹ",
    "453": "аҪЈаҫҹаҪҙ",
    "454": "аҪҰаҫҹ",
    "455": "аҪҰаҫҹаҪҙ",
    "456": "аҪҗаҪҙ",
    "457": "аҪ‘аҪҙ",
    "458": "аҪ‘аҫІ",
    "459": "аҪ‘аҫІаҪҙ",
    "460": "аҪўаҫЎ",
    "461": "аҪўаҫЎаҪҙ",
    "462": "аҪЈаҫЎ",
    "463": "аҪЈаҫЎаҪҙ",
    "464": "аҪҰаҫЎ",
    "465": "аҪҰаҫЎаҪҙ",
    "466": "аҪ“аҪҙ",
    "467": "аҪўаҫЈ",
    "468": "аҪўаҫЈаҪҙ",
    "469": "аҪҰаҫЈ",
    "470": "аҪҰаҫЈаҪҙ",
    "471": "аҪ”аҪҙ",
    "472": "аҪ”аҫІ",
    "473": "аҪ”аҫІаҪҙ",
    "474": "аҪ”аҫұ",
    "475": "аҪ”аҫұаҪҙ",
    "476": "аҪЈаҫӨ",
    "477": "аҪЈаҫӨаҪҙ",
    "478": "аҪҰаҫӨ",
    "479": "аҪҰаҫӨаҪҙ",
    "480": "аҪҰаҫӨаҫұ",
    "481": "аҪҰаҫӨаҫұаҪҙ",
    "482": "аҪҰаҫӨаҫІ",
    "483": "аҪҰаҫӨаҫІаҪҙ",
    "484": "аҪ•аҪҙ",
    "485": "аҪ•аҫұ",
    "486": "аҪ•аҫұаҪҙ",
    "487": "аҪ•аҫІ",
    "488": "аҪ•аҫІаҪҙ",
    "489": "аҪ–аҪҙ",
    "490": "аҪ–аҫұ",
    "491": "аҪ–аҫұаҪҙ",
    "492": "аҪ–аҫІ",
    "493": "аҪ–аҫІаҪҙ",
    "494": "аҪ–аҫі",
    "495": "аҪ–аҫіаҪҙ",
    "496": "аҪўаҫҰ",
    "497": "аҪўаҫҰаҪҙ",
    "498": "аҪЈаҫҰ",
    "499": "аҪЈаҫҰаҪҙ",
    "500": "аҪҰаҫҰ",
    "501": "аҪҰаҫҰаҪҙ",
    "502": "аҪҰаҫҰаҫұ",
    "503": "аҪҰаҫҰаҫұаҪҙ",
    "504": "аҪҰаҫҰаҫІ",
    "505": "аҪҰаҫҰаҫІаҪҙ",
    "506": "аҪҳаҪҙ",
    "507": "аҪҳаҫұ",
    "508": "аҪҳаҫұаҪҙ",
    "509": "аҪҳаҫІ",
    "510": "аҪҳаҫІаҪҙ",
    "511": "аҪўаҫЁ",
    "512": "аҪўаҫЁаҪҙ",
    "513": "аҪҰаҫЁ",
    "514": "аҪҰаҫЁаҪҙ",
    "515": "аҪҰаҫЁаҫұ",
    "516": "аҪҰаҫЁаҫұаҪҙ",
    "517": "аҪҰаҫЁаҫІ",
    "518": "аҪҰаҫЁаҫІаҪҙ",
    "519": "аҪҷаҪҙ",
    "520": "аҪўаҫ©",
    "521": "аҪўаҫ©аҪҙ",
    "522": "аҪҰаҫ©",
    "523": "аҪҰаҫ©аҪҙ",
    "524": "аҪҡаҪҙ",
    "525": "аҪӣаҪҙ",
    "526": "аҪўаҫ«",
    "527": "аҪўаҫ«аҪҙ",
    "528": "аҪқаҪҙ",
    "529": "аҪһаҪҙ",
    "530": "аҪҹаҪҙ",
    "531": "аҪҹаҫі",
    "532": "аҪҹаҫіаҪҙ",
    "533": "аҪ аҪҙ",
    "534": "аҪЎаҪҙ",
    "535": "аҪўаҪҙ",
    "536": "аҪўаҫі",
    "537": "аҪўаҫіаҪҙ",
    "538": "аҪЈаҪҙ",
    "539": "аҪӨаҪҙ",
    "540": "аҪҰаҪҙ",
    "541": "аҪҰаҫІ",
    "542": "аҪҰаҫІаҪҙ",
    "543": "аҪҰаҫі",
    "544": "аҪҰаҫіаҪҙ",
    "545": "аҪ§аҪҙ",
    "546": "аҪ§аҫІ",
    "547": "аҪ§аҫІаҪҙ",
    "548": "аҪЈаҫ·",
    "549": "аҪЈаҫ·аҪҙ",
    "550": "аҪЁаҪҙ",
    "551": "аҪӮаҫІаҫӯ",
    "552": "аҪўаҫ©аҫӯ",
    "553": "аҪўаҫЁаҫұ",
    "554": "аҪ•аҫұаҫӯ",
    "555": "аҪҖаҪұ",
    "556": "аҪӮаҪұ",
    "557": "аҪүаҪұ",
    "558": "аҪҸаҪұ",
    "559": "аҪ‘аҪұ",
    "560": "аҪ“аҪұ",
    "561": "аҪһаҪұ",
    "562": "аҪ§аҪұ",
    "563": "аҪҖаҫӯ",
    "564": "аҪҒаҫӯ",
    "565": "аҪӮаҫӯ",
    "566": "аҪүаҫӯ",
    "567": "аҪ‘аҫӯ",
    "568": "аҪҡаҫӯ",
    "569": "аҪһаҫӯ",
    "570": "аҪҹаҫӯ",
    "571": "аҪўаҫӯ",
    "572": "аҪЈаҫӯ",
    "573": "аҪӨаҫӯ",
    "574": "аҪ§аҫӯ",
    "575": "аҪ“аҫІ",
    "576": "аҪҰаҫЈаҫІ",
    "577": "аҪ§аҪұаҪҙ",
    "578": "аҪҖ",
    "579": "аҪҒ",
    "580": "аҪӮ",
    "581": "аҪ„",
    "582": "аҪ…",
    "583": "аҪҶ",
    "584": "аҪҮ",
    "585": "аҪү",
    "586": "аҪҸ",
    "587": "аҪҗ",
    "588": "аҪ‘",
    "589": "аҪ“",
    "590": "аҪ”",
    "591": "аҪ•",
    "592": "аҪ–",
    "593": "аҪҳ",
    "594": "аҪҷ",
    "595": "аҪҡ",
    "596": "аҪӣ",
    "597": "аҪқ",
    "598": "аҪһ",
    "599": "аҪҹ",
    "600": "аҪ ",
    "601": "аҪЎ",
    "602": "аҪў",
    "603": "аҪЈ",
    "604": "аҪӨ",
    "605": "аҪҘ",
    "606": "аҪҰ",
    "607": "аҪ§",
    "608": "аҪЁ",
    "609": "аҪў",
    "610": "аҪҖ",
    "611": "аҪҒ",
    "612": "аҪӮ",
    "613": "аҪ„",
    "614": "аҪ…",
    "615": "аҪҶ",
    "616": "аҪҮ",
    "617": "аҪү",
    "618": "аҪҗ",
    "619": "аҪ‘",
    "620": "аҪ“",
    "621": "аҪ”",
    "622": "аҪ•",
    "623": "аҪ–",
    "624": "аҪҳ",
    "625": "аҪҷ",
    "626": "аҪҡ",
    "627": "аҪӣ",
    "628": "аҪқ",
    "629": "аҪһ",
    "630": "аҪҹ",
    "631": "аҪ ",
    "632": "аҪЎ",
    "633": "аҪў",
    "634": "аҪЈ",
    "635": "аҪӨ",
    "636": "аҪҘ",
    "637": "аҪҰ",
    "638": "аҪ§",
    "639": "аҪЁ",
    "640": "аҪў",
    "642": "аҪҖ",
    "643": "аҪҒ",
    "644": "аҪӮ",
    "645": "аҪ„",
    "646": "аҪ…",
    "647": "аҪҶ",
    "648": "аҪҮ",
    "649": "аҪү",
    "650": "аҪҸ",
    "651": "аҪҗ",
    "652": "аҪ‘",
    "653": "аҪ“",
    "654": "аҪ”",
    "655": "аҪ•",
    "656": "аҪ–",
    "657": "аҪҳ",
    "658": "аҪҷ",
    "659": "аҪҡ",
    "660": "аҪӣ",
    "661": "аҪқ",
    "662": "аҪһ",
    "663": "аҪҹ",
    "664": "аҪ ",
    "665": "аҪЎ",
    "666": "аҪў",
    "667": "аҪЈ",
    "668": "аҪӨ",
    "669": "аҪҘ",
    "670": "аҪҰ",
    "671": "аҪ§",
    "672": "аҪЁ",
    "673": "аҪў",
    "675": "аҫҗ",
    "676": "аҫ‘",
    "677": "аҫ’",
    "678": "аҫ”",
    "679": "аҫ•",
    "680": "аҫ–",
    "681": "аҫ—",
    "682": "аҫҷ",
    "683": "аҫҹ",
    "684": "аҫ ",
    "685": "аҫЎ",
    "686": "аҫЈ",
    "687": "аҫӨ",
    "688": "аҫҘ",
    "689": "аҫҰ",
    "690": "аҫЁ",
    "691": "аҫ©",
    "692": "аҫӘ",
    "693": "аҫ«",
    "694": "аҫӯ",
    "695": "аҫ®",
    "696": "аҫҜ",
    "697": "аҫ°",
    "698": "аҫұ",
    "699": "аҫІ",
    "700": "аҫі",
    "701": "аҫҙ",
    "702": "аҫө",
    "703": "аҫ¶",
    "704": "аҫ·",
    "705": "аҫё",
    "706": "аҫә",
    "707": "аҫ»",
    "708": "аҫј",
    "709": "аҪҙ",
    "710": "аҪҙ",
    "711": "аҪұ",
    "712": "аҫҗ",
    "713": "аҫ‘",
    "714": "аҫ’",
    "715": "аҫ”",
    "716": "аҫ•",
    "717": "аҫ–",
    "718": "аҫ—",
    "719": "аҫҷ",
    "720": "аҫҹ",
    "721": "аҫ ",
    "722": "аҫЎ",
    "723": "аҫЈ",
    "724": "аҫӨ",
    "725": "аҫҘ",
    "726": "аҫҰ",
    "727": "аҫЁ",
    "728": "аҫ©",
    "729": "аҫӘ",
    "730": "аҫ«",
    "731": "аҫӯ",
    "732": "аҫ®",
    "733": "аҫҜ",
    "734": "аҫ°",
    "735": "аҫұ",
    "736": "аҫІ",
    "737": "аҫі",
    "738": "аҫҙ",
    "739": "аҫө",
    "740": "аҫ¶",
    "741": "аҫ·",
    "742": "аҫё",
    "743": "аҫә",
    "744": "аҫ»",
    "745": "аҫј",
    "746": "аҪҙ",
    "747": "аҪҙ",
    "748": "аҪұ",
    "749": "аҪҖаҫӯ",
    "750": "аҪҒаҫӯ",
    "751": "аҪӮаҫӯ",
    "752": "аҪүаҫӯ",
    "753": "аҪ‘аҫӯ",
    "754": "аҪҡаҫӯ",
    "755": "аҪһаҫӯ",
    "756": "аҪҹаҫӯ",
    "757": "аҪўаҫӯ",
    "758": "аҪЈаҫӯ",
    "759": "аҪӨаҫӯ",
    "760": "аҪ§аҫӯ",
    "761": "аҪҖаҫұ",
    "762": "аҪҒаҫұ",
    "763": "аҪӮаҫұ",
    "764": "аҪ”аҫұ",
    "765": "аҪ•аҫұ",
    "766": "аҪ–аҫұ",
    "767": "аҪҳаҫұ",
    "768": "аҪҖаҫІ",
    "769": "аҪҒаҫІ",
    "770": "аҪӮаҫІ",
    "772": "аҪҗаҫІ",
    "773": "аҪ‘аҫІ",
    "774": "аҪ“аҫІ",
    "775": "аҪ”аҫІ",
    "776": "аҪ•аҫІ",
    "777": "аҪ–аҫІ",
    "778": "аҪҳаҫІ",
    "779": "аҪҰаҫІ",
    "780": "аҪ§аҫІ",
    "781": "аҝҺ",
    "782": "аҝҗ",
    "783": "аҝ‘",
    "784": "аҝ’",
    "785": "аҝ“",
    "786": "аҝ”",
    "791": "аҝҷ",
    "792": "аҝҡ"
  },
  "_meta": {
    "source": "tibetan-fonts-main.zip::tibetan-fonts-main/Unicode Font Families & Typefaces/Bhod Dhorchang's Fonts/Bhozuk Wumchuma.ttf",
    "gids_mapped": 783,
    "multi_char_stacks": 230,
    "gsub_lookup_counts": {
      "1": 16,
      "2": 1,
      "3": 2,
      "4": 4,
      "6": 18
    }
  }
}