{
  "kokonor": {
    "1": "\u0000",
    "2": "\r",
    "3": " ",
    "5": "‌",
    "6": "‍",
    "7": "◌",
    "16": "ༀ",
    "17": "༁",
    "18": "༂",
    "19": "༃",
    "20": "༄",
    "21": "༅",
    "22": "༆",
    "23": "༇",
    "24": "༈",
    "25": "༉",
    "26": "༊",
    "27": "་",
    "28": "༌",
    "29": "།",
    "30": "༎",
    "31": "༏",
    "32": "༐",
    "33": "༑",
    "34": "༒",
    "35": "༓",
    "36": "༔",
    "37": "༕",
    "38": "༖",
    "39": "༗",
    "40": "༘",
    "41": "༙",
    "42": "༚",
    "43": "༛",
    "44": "༜",
    "45": "༝",
    "46": "༞",
    "47": "༟",
    "48": "༠",
    "49": "༡",
    "50": "༢",
    "51": "༣",
    "52": "༤",
    "53": "༥",
    "54": "༦",
    "55": "༧",
    "56": "༨",
    "57": "༩",
    "58": "༪",
    "59": "༫",
    "60": "༬",
    "61": "༭",
    "62": "༮",
    "63": "༯",
    "64": "༰",
    "65": "༱",
    "66": "༲",
    "67": "༳",
    "68": "༴",
    "69": "༵",
    "70": "༶",
    "71": "༷",
    "72": "༸",
    "73": "༹",
    "74": "༺",
    "75": "༻",
    "76": "༼",
    "77": "༽",
    "78": "༾",
    "79": "༿",
    "80": "ཀ",
    "81": "ཁ",
    "82": "ག",
    "83": "གྷ",
    "84": "ང",
    "85": "ཅ",
    "86": "ཆ",
    "87": "ཇ",
    "89": "ཉ",
    "90": "ཊ",
    "91": "ཋ",
    "92": "ཌ",
    "93": "ཌྷ",
    "94": "ཎ",
    "95": "ཏ",
    "96": "ཐ",
    "97": "ད",
    "98": "དྷ",
    "99": "ན",
    "100": "པ",
    "101": "ཕ",
    "102": "བ",
    "103": "བྷ",
    "104": "མ",
    "105": "ཙ",
    "106": "ཚ",
    "107": "ཛ",
    "108": "ཛྷ",
    "109": "ཝ",
    "110": "ཞ",
    "111": "ཟ",
    "112": "འ",
    "113": "ཡ",
    "114": "ར",
    "115": "ལ",
    "116": "ཤ",
    "117": "ཥ",
    "118": "ས",
    "119": "ཧ",
    "120": "ཨ",
    "121": "ཀྵ",
    "122": "ཪ",
    "129": "ཱ",
    "130": "ི",
    "131": "ཱི",
    "132": "ུ",
    "133": "ཱུ",
    "134": "ྲྀ",
    "135": "ཷ",
    "136": "ླྀ",
    "137": "ཹ",
    "138": "ེ",
    "139": "ཻ",
    "140": "ོ",
    "141": "ཽ",
    "142": "ཾ",
    "143": "ཿ",
    "144": "ྀ",
    "145": "ཱྀ",
    "146": "ྂ",
    "147": "ྃ",
    "148": "྄",
    "149": "྅",
    "150": "྆",
    "151": "྇",
    "152": "ྈ",
    "153": "ྉ",
    "154": "ྊ",
    "155": "ྋ",
    "160": "ྐ",
    "161": "ྑ",
    "162": "ྒ",
    "163": "ྒྷ",
    "164": "ྔ",
    "165": "ྕ",
    "166": "ྖ",
    "167": "ྗ",
    "169": "ྙ",
    "170": "ྚ",
    "171": "ྛ",
    "172": "ྜ",
    "173": "ྜྷ",
    "174": "ྞ",
    "175": "ྟ",
    "176": "ྠ",
    "177": "ྡ",
    "178": "ྡྷ",
    "179": "ྣ",
    "180": "ྤ",
    "181": "ྥ",
    "182": "ྦ",
    "183": "ྦྷ",
    "184": "ྨ",
    "185": "ྩ",
    "186": "ྪ",
    "187": "ྫ",
    "188": "ྫྷ",
    "189": "ྭ",
    "190": "ྮ",
    "191": "ྯ",
    "192": "ྰ",
    "193": "ྱ",
    "194": "ྲ",
    "195": "ླ",
    "196": "ྴ",
    "197": "ྵ",
    "198": "ྶ",
    "199": "ྷ",
    "200": "ྸ",
    "201": "ྐྵ",
    "202": "ྺ",
    "203": "ྻ",
    "204": "ྼ",
    "206": "྾",
    "207": "྿",
    "208": "࿀",
    "209": "࿁",
    "210": "࿂",
    "211": "࿃",
    "212": "࿄",
    "213": "࿅",
    "214": "࿆",
    "215": "࿇",
    "216": "࿈",
    "217": "࿉",
    "218": "࿊",
    "219": "࿋",
    "220": "࿌",
    "223": "࿏",
    "224": "࿐",
    "225": "࿑"
  },
  "_meta": {
    "lookup_kind": "gid",
    "source": "tibetan-fonts-main.zip::tibetan-fonts-main/Unicode Individual fonts/kokonor.ttf",
    "gids_mapped": 201,
    "multi_char_stacks": 0,
    "gsub_lookup_counts": {}
  }
}