{
  "landza87": {
    "3": " ",
    "4": "!",
    "5": "0",
    "6": "1",
    "7": "2",
    "8": "3",
    "9": "4",
    "10": "5",
    "11": ":",
    "12": ";",
    "13": "<",
    "14": "=",
    "15": ">",
    "16": "?",
    "17": "@",
    "18": "A",
    "19": "B",
    "20": "C",
    "21": "D",
    "22": "E",
    "23": "J",
    "24": "K",
    "25": "L",
    "26": "M",
    "27": "N",
    "28": "O",
    "29": "P",
    "30": "Q",
    "31": "R",
    "32": "S",
    "33": "T",
    "34": "U",
    "35": "Z",
    "36": "[",
    "37": "\\",
    "38": "]",
    "39": "^",
    "40": "_",
    "41": "`",
    "42": "a",
    "43": "b",
    "44": "c",
    "45": "d",
    "46": "e",
    "47": "j",
    "48": "k",
    "49": "l",
    "50": "m",
    "51": "n",
    "52": "o",
    "53": "p",
    "54": "q",
    "55": "r",
    "56": "s",
    "57": "t",
    "58": "u",
    "59": "v",
    "60": "w",
    "61": "x",
    "62": "y",
    "63": "z",
    "64": "{",
    "65": "|",
    "66": "}",
    "67": "~",
    "68": "",
    "69": "",
    "70": "",
    "71": "‚",
    "72": "ƒ",
    "73": "„",
    "74": "…",
    "75": "†",
    "76": "‡",
    "77": "ˆ",
    "78": "‰",
    "79": "Š",
    "80": "‹",
    "81": "Œ",
    "82": "",
    "83": "",
    "84": "",
    "85": "",
    "86": "‘",
    "87": "’",
    "88": "“",
    "89": "”",
    "90": "•",
    "91": "–",
    "92": "—",
    "93": "˜",
    "94": "™",
    "95": "š",
    "96": "›",
    "97": "œ",
    "98": "",
    "99": "",
    "100": "Ÿ",
    "101": " ",
    "102": "¡",
    "103": "¢",
    "104": "£",
    "105": "¤",
    "106": "¥",
    "107": "¦",
    "108": "§",
    "109": "¨",
    "110": "©",
    "111": "ª",
    "112": "«",
    "113": "¬",
    "114": "­",
    "115": "®",
    "116": "¯"
  },
  "_meta": {
    "lookup_kind": "gid",
    "source": "tibetan-fonts-main.zip::tibetan-fonts-main/Non-Unicode Fonts/Landza/landza87.ttf",
    "gids_mapped": 114,
    "multi_char_stacks": 0,
    "gsub_lookup_counts": {}
  }
}