{
  "monlamtigmachoug2": {
    "3": " ",
    "4": "!",
    "5": "\"",
    "6": "#",
    "7": "$",
    "8": "%",
    "9": "&",
    "10": "'",
    "11": "(",
    "12": ")",
    "13": "*",
    "14": "+",
    "15": ",",
    "17": ".",
    "18": "/",
    "19": "0",
    "20": "1",
    "21": "2",
    "22": "3",
    "23": "4",
    "24": "5",
    "25": "6",
    "26": "7",
    "27": "8",
    "28": "9",
    "29": ":",
    "30": ";",
    "31": "<",
    "32": "=",
    "33": ">",
    "34": "?",
    "35": "@",
    "36": "A",
    "37": "B",
    "38": "C",
    "39": "D",
    "40": "E",
    "41": "F",
    "42": "G",
    "43": "H",
    "44": "I",
    "45": "J",
    "46": "K",
    "47": "L",
    "48": "[",
    "49": "\\",
    "50": "]",
    "51": "^",
    "52": "_",
    "53": "`",
    "54": "a",
    "55": "b",
    "56": "c",
    "57": "d",
    "58": "e",
    "59": "f",
    "60": "g",
    "61": "h",
    "62": "i",
    "63": "j",
    "64": "k",
    "65": "l",
    "66": "m",
    "67": "n",
    "68": "o",
    "69": "p",
    "70": "q",
    "71": "r",
    "72": "s",
    "73": "t",
    "74": "u",
    "75": "v",
    "76": "w",
    "77": "x",
    "78": "y",
    "79": "z",
    "80": "{",
    "81": "|",
    "82": "}",
    "83": "~",
    "84": "┬κ",
    "85": "┬λ",
    "86": "┬μ",
    "87": "┬ν",
    "88": "┬ξ",
    "89": "┬ο",
    "90": "┬π",
    "91": "┬ρ",
    "92": "┬σ",
    "93": "┬ς",
    "94": "┬τ",
    "95": "┬υ",
    "96": "┬χ",
    "98": "┬░",
    "99": "┬▒",
    "100": "┬▓",
    "101": "┬│",
    "102": "┬┤",
    "104": "┬╢",
    "105": "έΙβ",
    "106": "┬╕",
    "107": "┬╣",
    "108": "┬║",
    "109": "┬╗",
    "110": "┬╝",
    "111": "┬╜",
    "112": "┬╛",
    "113": "┬┐",
    "114": "├Α",
    "115": "├Β",
    "116": "├Γ",
    "117": "├Δ",
    "118": "├Ε",
    "119": "├Ζ",
    "120": "├Η",
    "121": "├Θ",
    "122": "├Ι",
    "123": "├Κ",
    "124": "├Λ",
    "125": "├Μ",
    "126": "├Ν",
    "127": "├Ξ",
    "128": "├Ο",
    "129": "├Π",
    "130": "├Ρ",
    "131": "├Σ",
    "132": "├Τ",
    "133": "├Υ",
    "134": "├Φ",
    "135": "├Χ",
    "136": "├Ψ",
    "137": "├Ω",
    "138": "├α",
    "139": "├β",
    "140": "├γ",
    "141": "├δ",
    "142": "├ε",
    "143": "├ζ",
    "144": "├η",
    "145": "├θ",
    "146": "├ι",
    "147": "├κ",
    "148": "├λ",
    "149": "├μ",
    "150": "├ν",
    "151": "├ξ",
    "152": "├ο",
    "153": "├π",
    "154": "├ρ",
    "155": "├σ",
    "156": "├ς",
    "157": "├τ",
    "158": "├υ",
    "159": "├φ",
    "160": "├χ",
    "161": "├ψ",
    "162": "├░",
    "163": "├▒",
    "164": "├▓",
    "165": "├│",
    "166": "├┤",
    "167": "├╡",
    "168": "├╢",
    "169": "├╖",
    "170": "├╕",
    "171": "├╣",
    "172": "├║",
    "173": "├╗",
    "174": "├╝",
    "175": "├╜",
    "176": "├╛",
    "177": "├┐",
    "178": "─Α",
    "179": "─Β",
    "180": "─Γ",
    "181": "─Δ",
    "182": "─Ε",
    "183": "─Ζ",
    "184": "─Η",
    "185": "─Θ",
    "186": "┼Τ",
    "187": "┼Υ",
    "188": "┼ι",
    "189": "┼κ",
    "190": "┼╕",
    "191": "╞Τ",
    "192": "╦Η",
    "193": "╦Κ",
    "194": "╦ε",
    "195": "╬Χ",
    "196": "╬ζ",
    "197": "έΑΥ",
    "198": "έΑΦ",
    "199": "έΑα",
    "200": "έΑβ",
    "201": "έΑγ",
    "202": "έΑη",
    "203": "έΑι",
    "204": "έΑκ",
    "205": "έΑλ",
    "206": "έΑο",
    "207": "έΑ░",
    "208": "έΑ╣",
    "209": "έΑ║",
    "210": "έΕλ",
    "243": "┬Ξ",
    "244": "┬ι",
    "245": "┬ψ",
    "246": "╬╝",
    "247": "έΑΡ"
  },
  "_meta": {
    "lookup_kind": "gid",
    "source": "tibetan-fonts-main.zip::tibetan-fonts-main/Non-Unicode Fonts/Monlam/Monlam Tigma-choug 2.TTF",
    "gids_mapped": 210,
    "multi_char_stacks": 0,
    "gsub_lookup_counts": {}
  }
}