{
  "tdia2": {
    "3": " ",
    "4": "o",
    "5": "p",
    "6": "q",
    "7": "t",
    "8": "u",
    "9": "A",
    "10": "D",
    "11": "H",
    "12": "I",
    "13": "K",
    "14": "L",
    "15": "M",
    "16": "N",
    "17": "O",
    "18": "P",
    "19": "Q",
    "20": "R",
    "21": "S",
    "22": "T",
    "23": "U",
    "24": "m",
    "25": "r",
    "26": "s",
    "27": "a",
    "28": "d",
    "29": "h",
    "30": "n",
    "31": "i",
    "32": "k",
    "33": "l",
    "34": " "
  },
  "_meta": {
    "source": "tibetan-fonts-main.zip::tibetan-fonts-main/Non-Unicode Fonts/TNRDia/TDIA2.TTF",
    "gids_mapped": 32,
    "multi_char_stacks": 0,
    "gsub_lookup_counts": {}
  }
}