{
  "ticgcs1": {
    "1": " ",
    "2": "!",
    "3": "\"",
    "4": "#",
    "5": "$",
    "6": "%",
    "7": "&",
    "8": "'",
    "9": "(",
    "10": ")",
    "11": "*",
    "12": "+",
    "13": ",",
    "14": "├╝",
    "15": ".",
    "16": "/",
    "17": "0",
    "18": "1",
    "19": "2",
    "20": "3",
    "21": "4",
    "22": "5",
    "23": "6",
    "24": "7",
    "25": "8",
    "26": "9",
    "27": ":",
    "28": ";",
    "29": "<",
    "30": "=",
    "31": ">",
    "32": "?",
    "33": "@",
    "34": "A",
    "35": "B",
    "36": "C",
    "37": "D",
    "38": "E",
    "39": "F",
    "40": "G",
    "41": "H",
    "42": "I",
    "43": "J",
    "44": "K",
    "45": "L",
    "46": "M",
    "47": "N",
    "48": "O",
    "49": "P",
    "50": "Q",
    "51": "R",
    "52": "S",
    "53": "T",
    "54": "U",
    "55": "V",
    "56": "W",
    "57": "X",
    "58": "Y",
    "59": "Z",
    "60": "[",
    "61": "\\",
    "62": "]",
    "63": "^",
    "64": "_",
    "65": "`",
    "66": "a",
    "67": "b",
    "68": "c",
    "69": "d",
    "70": "e",
    "71": "f",
    "72": "g",
    "73": "h",
    "74": "i",
    "75": "j",
    "76": "k",
    "77": "l",
    "78": "m",
    "79": "n",
    "80": "o",
    "81": "p",
    "82": "q",
    "83": "r",
    "84": "s",
    "85": "t",
    "86": "u",
    "87": "v",
    "88": "w",
    "89": "x",
    "90": "y",
    "91": "z",
    "92": "{",
    "93": "|",
    "94": "}",
    "95": "~",
    "96": "├й",
    "97": "Рѓг",
    "98": "Ьђљ",
    "99": "Рђџ",
    "100": "књ",
    "101": "Рђъ",
    "102": "Рђд",
    "103": "Рђа",
    "104": "РђА",
    "105": "╦є",
    "106": "Рђ░",
    "107": "┼а",
    "108": "Рђ╣",
    "109": "┼њ",
    "110": "ЬђЉ",
    "111": "├╣",
    "112": "Ьђњ",
    "113": "ЬђЊ",
    "114": "Рђў",
    "115": "РђЎ",
    "116": "Рђю",
    "117": "РђЮ",
    "118": "Рђб",
    "119": "РђЊ",
    "120": "Рђћ",
    "121": "╦ю",
    "122": "Рёб",
    "123": "┼А",
    "124": "Рђ║",
    "125": "┼Њ",
    "126": "Ьђћ",
    "127": "├║",
    "128": "┼И",
    "129": "├Й",
    "130": "┬А",
    "131": "┬б",
    "132": "┬Б",
    "133": "┬ц",
    "134": "┬Ц",
    "135": "├╗",
    "136": "┬Д",
    "137": "┬е",
    "138": "┬Е",
    "139": "┬ф",
    "140": "┬Ф",
    "141": "┬г",
    "142": "┬Г",
    "143": "┬«",
    "144": "┬»",
    "145": "┬░",
    "146": "┬▒",
    "147": "┬▓",
    "148": "┬│",
    "149": "┬┤",
    "150": "╬╝",
    "151": "┬Х",
    "152": "┬и",
    "153": "┬И",
    "154": "┬╣",
    "155": "┬║",
    "156": "┬╗",
    "157": "┬╝",
    "158": "┬й",
    "159": "┬Й",
    "160": "┬┐",
    "161": "├ђ",
    "162": "├Ђ",
    "163": "├ѓ",
    "164": "├Ѓ",
    "165": "├ё",
    "166": "├Ё",
    "167": "├є",
    "168": "├Є",
    "169": "├Ѕ",
    "170": "├і",
    "171": "├І",
    "172": "├ї",
    "173": "├Ї",
    "174": "├ј",
    "175": "├Ј",
    "176": "├Њ",
    "177": "├ћ",
    "178": "├Ћ",
    "179": "├ќ",
    "180": "├Ќ",
    "181": "├ў",
    "182": "├Ў",
    "183": "├а",
    "184": "├А",
    "185": "├б",
    "186": "├Б",
    "187": "├ц",
    "188": "├Ц",
    "189": "├д",
    "190": "├љ",
    "191": "┬а"
  },
  "_meta": {
    "source": "tibetan-fonts-private-main.zip::tibetan-fonts-private-main/PKTC_Tibetan_Font_Bundle/Tibetan Classic/TCC non-unicode/TICGCS1.ttf",
    "gids_mapped": 191,
    "multi_char_stacks": 0,
    "gsub_lookup_counts": {}
  }
}